asfv1.py
asfv1-1.2.7.dist-info/LICENSE
asfv1-1.2.7.dist-info/METADATA
asfv1-1.2.7.dist-info/WHEEL
asfv1-1.2.7.dist-info/entry_points.txt
asfv1-1.2.7.dist-info/top_level.txt
asfv1-1.2.7.dist-info/RECORD
