Metadata-Version: 2.1
Name: asfv1
Version: 1.2.7
Summary: Alternate FV-1 Assembler
Home-page: https://github.com/ndf-zz/asfv1
Author: Nathan Fraser
Author-email: ndf@metarace.com.au
License: UNKNOWN
Platform: UNKNOWN
Classifier: Development Status :: 5 - Production/Stable
Classifier: Environment :: Console
Classifier: License :: OSI Approved :: GNU Lesser General Public License v3 or later (LGPLv3+)
Classifier: Programming Language :: Python
Classifier: Topic :: Software Development :: Assemblers
Requires-Python: >=2.6
